bugfinder/__init__.py
bugfinder/asrsummary.py
bugfinder/auth.py
bugfinder/sql.py
bugfinder/utils.py
bugfinder/apps/__init__.py
bugfinder/apps/monitor.py
bugfinder/base/__init__.py
bugfinder-0.0.14.dist-info/METADATA
bugfinder-0.0.14.dist-info/WHEEL
bugfinder-0.0.14.dist-info/entry_points.txt
bugfinder-0.0.14.dist-info/top_level.txt
bugfinder-0.0.14.dist-info/RECORD
